{
 "started_at": "2021-11-13T08:01:33+00:00",
 "state": "completed",
 "status": [
  {
   "name": "maf2synteny",
   "platform": "linux-64",
   "status": [
    {
     "implementation": "mamba",
     "package": {
      "build": "h1b792b2_0",
      "build_number": 0,
      "channel": "https://conda.anaconda.org/bioconda/linux-64",
      "name": "maf2synteny",
      "subdir": "linux-64",
      "version": "1.2"
     },
     "solve": "success",
     "test": "success"
    }
   ]
  },
  {
   "name": "maf2synteny",
   "platform": "osx-64",
   "status": [
    {
     "implementation": "mamba",
     "package": {
      "build": "h589c0e0_0",
      "build_number": 0,
      "channel": "https://conda.anaconda.org/bioconda/osx-64",
      "name": "maf2synteny",
      "subdir": "osx-64",
      "version": "1.2"
     },
     "solve": "success",
     "test": "success"
    }
   ]
  }
 ]
}