{
 "started_at": "2021-11-18T18:16:21+00:00",
 "state": "completed",
 "status": [
  {
   "name": "ruby",
   "platform": "linux-64",
   "status": [
    {
     "implementation": "mamba",
     "package": {
      "build": "h86e321c_6",
      "build_number": 6,
      "channel": "https://conda.anaconda.org/conda-forge/linux-64",
      "name": "ruby",
      "subdir": "linux-64",
      "version": "2.7.2"
     },
     "solve": "success",
     "test": "success"
    }
   ]
  },
  {
   "name": "ruby",
   "platform": "osx-64",
   "status": [
    {
     "implementation": "mamba",
     "package": {
      "build": "h1c0b240_6",
      "build_number": 6,
      "channel": "https://conda.anaconda.org/conda-forge/osx-64",
      "name": "ruby",
      "subdir": "osx-64",
      "version": "2.7.2"
     },
     "solve": "success",
     "test": "success"
    }
   ]
  }
 ]
}