{
 "started_at": "2021-11-23T16:46:26+00:00",
 "state": "completed",
 "status": [
  {
   "name": "gargammel",
   "platform": "linux-64",
   "status": [
    {
     "implementation": "mamba",
     "package": {
      "build": "hc6adf06_3",
      "build_number": 3,
      "channel": "https://conda.anaconda.org/bioconda/linux-64",
      "name": "gargammel",
      "subdir": "linux-64",
      "version": "1.1.2"
     },
     "solve": "success",
     "test": "failed"
    }
   ]
  },
  {
   "name": "gargammel",
   "platform": "osx-64",
   "status": [
    {
     "implementation": "mamba",
     "package": {
      "build": "hdd5f81f_3",
      "build_number": 3,
      "channel": "https://conda.anaconda.org/bioconda/osx-64",
      "name": "gargammel",
      "subdir": "osx-64",
      "version": "1.1.2"
     },
     "solve": "success",
     "test": "failed"
    }
   ]
  }
 ]
}