{
 "started_at": "2021-11-21T21:46:14+00:00",
 "state": "completed",
 "status": [
  {
   "name": "dialign-tx",
   "platform": "linux-64",
   "status": [
    {
     "implementation": "mamba",
     "package": {
      "build": "h779adbc_4",
      "build_number": 4,
      "channel": "https://conda.anaconda.org/bioconda/linux-64",
      "name": "dialign-tx",
      "subdir": "linux-64",
      "version": "1.0.2"
     },
     "solve": "success",
     "test": "failed"
    }
   ]
  },
  {
   "name": "dialign-tx",
   "platform": "osx-64",
   "status": [
    {
     "implementation": "mamba",
     "package": {
      "build": "hb4d813b_4",
      "build_number": 4,
      "channel": "https://conda.anaconda.org/bioconda/osx-64",
      "name": "dialign-tx",
      "subdir": "osx-64",
      "version": "1.0.2"
     },
     "solve": "success",
     "test": "failed"
    }
   ]
  }
 ]
}