{
 "started_at": "2021-11-18T23:31:22+00:00",
 "state": "completed",
 "status": [
  {
   "name": "htslib",
   "platform": "linux-64",
   "status": [
    {
     "implementation": "mamba",
     "package": {
      "build": "h9093b5e_0",
      "build_number": 0,
      "channel": "https://conda.anaconda.org/bioconda/linux-64",
      "name": "htslib",
      "subdir": "linux-64",
      "version": "1.14"
     },
     "solve": "success",
     "test": "failed"
    }
   ]
  },
  {
   "name": "htslib",
   "platform": "osx-64",
   "status": [
    {
     "implementation": "mamba",
     "package": {
      "build": "hc38c3fb_0",
      "build_number": 0,
      "channel": "https://conda.anaconda.org/bioconda/osx-64",
      "name": "htslib",
      "subdir": "osx-64",
      "version": "1.14"
     },
     "solve": "success",
     "test": "failed"
    }
   ]
  }
 ]
}