{
 "started_at": "2021-10-30T14:46:14+00:00",
 "state": "completed",
 "status": [
  {
   "name": "hopla",
   "platform": "linux-64",
   "status": [
    {
     "implementation": "mamba",
     "package": {
      "build": "hdfd78af_0",
      "build_number": 0,
      "channel": "https://conda.anaconda.org/bioconda/noarch",
      "name": "hopla",
      "subdir": "noarch",
      "version": "1.0.6"
     },
     "solve": "success",
     "test": "success"
    }
   ]
  },
  {
   "name": "hopla",
   "platform": "osx-64",
   "status": [
    {
     "implementation": "mamba",
     "package": {
      "build": "hdfd78af_0",
      "build_number": 0,
      "channel": "https://conda.anaconda.org/bioconda/noarch",
      "name": "hopla",
      "subdir": "noarch",
      "version": "1.0.6"
     },
     "solve": "success",
     "test": "success"
    }
   ]
  }
 ]
}