{
 "started_at": "2021-11-11T20:01:19+00:00",
 "state": "completed",
 "status": [
  {
   "name": "samwell",
   "platform": "linux-64",
   "status": [
    {
     "implementation": "mamba",
     "package": {
      "build": "py38h0213d0e_0",
      "build_number": 0,
      "channel": "https://conda.anaconda.org/bioconda/linux-64",
      "name": "samwell",
      "subdir": "linux-64",
      "version": "0.0.2"
     },
     "solve": "success",
     "test": "success"
    }
   ]
  },
  {
   "name": "samwell",
   "platform": "osx-64",
   "status": [
    {
     "implementation": "mamba",
     "package": {
      "build": "py38h771b250_0",
      "build_number": 0,
      "channel": "https://conda.anaconda.org/bioconda/osx-64",
      "name": "samwell",
      "subdir": "osx-64",
      "version": "0.0.2"
     },
     "solve": "success",
     "test": "success"
    }
   ]
  }
 ]
}