{
 "started_at": "2021-11-11T17:16:19+00:00",
 "state": "completed",
 "status": [
  {
   "name": "scorpio",
   "platform": "linux-64",
   "status": [
    {
     "implementation": "mamba",
     "package": {
      "build": "pyhdfd78af_0",
      "build_number": 0,
      "channel": "https://conda.anaconda.org/bioconda/noarch",
      "name": "scorpio",
      "subdir": "noarch",
      "version": "0.3.14"
     },
     "solve": "success",
     "test": "success"
    }
   ]
  },
  {
   "name": "scorpio",
   "platform": "osx-64",
   "status": [
    {
     "implementation": "mamba",
     "package": {
      "build": "pyhdfd78af_0",
      "build_number": 0,
      "channel": "https://conda.anaconda.org/bioconda/noarch",
      "name": "scorpio",
      "subdir": "noarch",
      "version": "0.3.14"
     },
     "solve": "success",
     "test": "success"
    }
   ]
  }
 ]
}