{
 "started_at": "2021-09-11T15:01:31+00:00",
 "state": "completed",
 "status": [
  {
   "name": "r-knitr",
   "platform": "linux-64",
   "status": [
    {
     "implementation": "mamba",
     "package": {
      "build": "r41hc72bb7e_0",
      "build_number": 0,
      "channel": "https://conda.anaconda.org/conda-forge/noarch",
      "name": "r-knitr",
      "subdir": "noarch",
      "version": "1.34"
     },
     "solve": "success",
     "test": "success"
    }
   ]
  },
  {
   "name": "r-knitr",
   "platform": "osx-64",
   "status": [
    {
     "implementation": "mamba",
     "package": {
      "build": "r41hc72bb7e_0",
      "build_number": 0,
      "channel": "https://conda.anaconda.org/conda-forge/noarch",
      "name": "r-knitr",
      "subdir": "noarch",
      "version": "1.34"
     },
     "solve": "success",
     "test": "success"
    }
   ]
  }
 ]
}