{
 "started_at": "2021-11-11T13:16:27+00:00",
 "state": "completed",
 "status": [
  {
   "name": "r-ldrtools",
   "platform": "linux-64",
   "status": [
    {
     "implementation": "mamba",
     "package": {
      "build": "r41hc72bb7e_1",
      "build_number": 1,
      "channel": "https://conda.anaconda.org/conda-forge/noarch",
      "name": "r-ldrtools",
      "subdir": "noarch",
      "version": "0.2_1"
     },
     "solve": "success",
     "test": "success"
    }
   ]
  },
  {
   "name": "r-ldrtools",
   "platform": "osx-64",
   "status": [
    {
     "implementation": "mamba",
     "package": {
      "build": "r41hc72bb7e_1",
      "build_number": 1,
      "channel": "https://conda.anaconda.org/conda-forge/noarch",
      "name": "r-ldrtools",
      "subdir": "noarch",
      "version": "0.2_1"
     },
     "solve": "success",
     "test": "success"
    }
   ]
  }
 ]
}