{
 "started_at": "2021-11-22T18:16:17+00:00",
 "state": "completed",
 "status": [
  {
   "name": "r-nbpseq",
   "platform": "linux-64",
   "status": [
    {
     "implementation": "mamba",
     "package": {
      "build": "r41hdf9a8c9_5",
      "build_number": 5,
      "channel": "https://conda.anaconda.org/bioconda/linux-64",
      "name": "r-nbpseq",
      "subdir": "linux-64",
      "version": "0.3.0"
     },
     "solve": "success",
     "test": "failed"
    }
   ]
  },
  {
   "name": "r-nbpseq",
   "platform": "osx-64",
   "status": [
    {
     "implementation": "mamba",
     "package": {
      "build": "r41h9e43be8_5",
      "build_number": 5,
      "channel": "https://conda.anaconda.org/bioconda/osx-64",
      "name": "r-nbpseq",
      "subdir": "osx-64",
      "version": "0.3.0"
     },
     "solve": "success",
     "test": "failed"
    }
   ]
  }
 ]
}