{
 "started_at": "2021-11-02T23:31:16+00:00",
 "state": "completed",
 "status": [
  {
   "name": "curves",
   "platform": "linux-64",
   "status": [
    {
     "implementation": "mamba",
     "package": {
      "build": "h8c3ec31_2",
      "build_number": 2,
      "channel": "https://conda.anaconda.org/bioconda/linux-64",
      "name": "curves",
      "subdir": "linux-64",
      "version": "3.0.0"
     },
     "solve": "success",
     "test": "success"
    }
   ]
  },
  {
   "name": "curves",
   "platform": "osx-64",
   "status": [
    {
     "implementation": "mamba",
     "package": {
      "build": "h17bd846_2",
      "build_number": 2,
      "channel": "https://conda.anaconda.org/bioconda/osx-64",
      "name": "curves",
      "subdir": "osx-64",
      "version": "3.0.0"
     },
     "solve": "success",
     "test": "success"
    }
   ]
  }
 ]
}