{
 "started_at": "2021-11-17T20:46:25+00:00",
 "state": "completed",
 "status": [
  {
   "name": "bioconductor-r3cseq",
   "platform": "linux-64",
   "status": [
    {
     "implementation": "mamba",
     "package": {
      "build": "r41hdfd78af_0",
      "build_number": 0,
      "channel": "https://conda.anaconda.org/bioconda/noarch",
      "name": "bioconductor-r3cseq",
      "subdir": "noarch",
      "version": "1.40.0"
     },
     "solve": "success",
     "test": "success"
    }
   ]
  },
  {
   "name": "bioconductor-r3cseq",
   "platform": "osx-64",
   "status": [
    {
     "implementation": "mamba",
     "package": {
      "build": "r41hdfd78af_0",
      "build_number": 0,
      "channel": "https://conda.anaconda.org/bioconda/noarch",
      "name": "bioconductor-r3cseq",
      "subdir": "noarch",
      "version": "1.40.0"
     },
     "solve": "success",
     "test": "success"
    }
   ]
  }
 ]
}