{
 "started_at": "2021-11-05T22:46:10+00:00",
 "state": "completed",
 "status": [
  {
   "name": "gnu-wget",
   "platform": "linux-64",
   "status": [
    {
     "implementation": "mamba",
     "package": {
      "build": "h5bf99c6_5",
      "build_number": 5,
      "channel": "https://conda.anaconda.org/bioconda/linux-64",
      "name": "gnu-wget",
      "subdir": "linux-64",
      "version": "1.18"
     },
     "solve": "success",
     "test": "success"
    }
   ]
  },
  {
   "name": "gnu-wget",
   "platform": "osx-64",
   "status": [
    {
     "implementation": "mamba",
     "package": {
      "build": "h188c3c3_5",
      "build_number": 5,
      "channel": "https://conda.anaconda.org/bioconda/osx-64",
      "name": "gnu-wget",
      "subdir": "osx-64",
      "version": "1.18"
     },
     "solve": "success",
     "test": "success"
    }
   ]
  }
 ]
}