{
 "started_at": "2021-10-05T13:01:23+00:00",
 "state": "completed",
 "status": [
  {
   "name": "eigensoft",
   "platform": "linux-64",
   "status": [
    {
     "implementation": "mamba",
     "package": {
      "build": "h767d0c5_3",
      "build_number": 3,
      "channel": "https://conda.anaconda.org/bioconda/linux-64",
      "name": "eigensoft",
      "subdir": "linux-64",
      "version": "7.2.1"
     },
     "solve": "success",
     "test": "failed"
    }
   ]
  },
  {
   "name": "eigensoft",
   "platform": "osx-64",
   "status": [
    {
     "implementation": "mamba",
     "package": {
      "build": "h556b040_3",
      "build_number": 3,
      "channel": "https://conda.anaconda.org/bioconda/osx-64",
      "name": "eigensoft",
      "subdir": "osx-64",
      "version": "7.2.1"
     },
     "solve": "success",
     "test": "failed"
    }
   ]
  }
 ]
}