{
 "started_at": "2021-11-10T18:01:22+00:00",
 "state": "completed",
 "status": [
  {
   "name": "r-flexmix",
   "platform": "linux-64",
   "status": [
    {
     "implementation": "mamba",
     "package": {
      "build": "r41hc72bb7e_0",
      "build_number": 0,
      "channel": "https://conda.anaconda.org/conda-forge/noarch",
      "name": "r-flexmix",
      "subdir": "noarch",
      "version": "2.3_17"
     },
     "solve": "success",
     "test": "success"
    }
   ]
  },
  {
   "name": "r-flexmix",
   "platform": "osx-64",
   "status": [
    {
     "implementation": "mamba",
     "package": {
      "build": "r41hc72bb7e_0",
      "build_number": 0,
      "channel": "https://conda.anaconda.org/conda-forge/noarch",
      "name": "r-flexmix",
      "subdir": "noarch",
      "version": "2.3_17"
     },
     "solve": "success",
     "test": "success"
    }
   ]
  }
 ]
}