{
 "started_at": "2021-11-20T21:46:25+00:00",
 "state": "completed",
 "status": [
  {
   "name": "ruffus",
   "platform": "linux-64",
   "status": [
    {
     "implementation": "mamba",
     "package": {
      "build": "pyh864c0ab_1",
      "build_number": 1,
      "channel": "https://conda.anaconda.org/bioconda/noarch",
      "name": "ruffus",
      "subdir": "noarch",
      "version": "2.8.4"
     },
     "solve": "success",
     "test": "failed"
    }
   ]
  },
  {
   "name": "ruffus",
   "platform": "osx-64",
   "status": [
    {
     "implementation": "mamba",
     "package": {
      "build": "pyh864c0ab_1",
      "build_number": 1,
      "channel": "https://conda.anaconda.org/bioconda/noarch",
      "name": "ruffus",
      "subdir": "noarch",
      "version": "2.8.4"
     },
     "solve": "success",
     "test": "failed"
    }
   ]
  }
 ]
}