{
 "started_at": "2021-11-18T03:16:28+00:00",
 "state": "completed",
 "status": [
  {
   "name": "bioconductor-mergemaid",
   "platform": "linux-64",
   "status": [
    {
     "implementation": "mamba",
     "package": {
      "build": "r40_0",
      "build_number": 0,
      "channel": "https://conda.anaconda.org/bioconda/noarch",
      "name": "bioconductor-mergemaid",
      "subdir": "noarch",
      "version": "2.59.0"
     },
     "solve": "success",
     "test": "success"
    }
   ]
  },
  {
   "name": "bioconductor-mergemaid",
   "platform": "osx-64",
   "status": [
    {
     "implementation": "mamba",
     "package": {
      "build": "r40_0",
      "build_number": 0,
      "channel": "https://conda.anaconda.org/bioconda/noarch",
      "name": "bioconductor-mergemaid",
      "subdir": "noarch",
      "version": "2.59.0"
     },
     "solve": "success",
     "test": "success"
    }
   ]
  }
 ]
}