{
 "started_at": "2021-10-24T21:46:12+00:00",
 "state": "completed",
 "status": [
  {
   "name": "ciso8601",
   "platform": "linux-64",
   "status": [
    {
     "implementation": "mamba",
     "package": {
      "build": "py39h3811e60_0",
      "build_number": 0,
      "channel": "https://conda.anaconda.org/conda-forge/linux-64",
      "name": "ciso8601",
      "subdir": "linux-64",
      "version": "2.2.0"
     },
     "solve": "success",
     "test": "success"
    }
   ]
  },
  {
   "name": "ciso8601",
   "platform": "osx-64",
   "status": [
    {
     "implementation": "mamba",
     "package": {
      "build": "py39h89e85a6_0",
      "build_number": 0,
      "channel": "https://conda.anaconda.org/conda-forge/osx-64",
      "name": "ciso8601",
      "subdir": "osx-64",
      "version": "2.2.0"
     },
     "solve": "success",
     "test": "success"
    }
   ]
  }
 ]
}