{
 "started_at": "2021-11-17T07:16:24+00:00",
 "state": "completed",
 "status": [
  {
   "name": "graphicsmagick",
   "platform": "linux-64",
   "status": [
    {
     "implementation": "mamba",
     "package": {
      "build": "hdc87540_2",
      "build_number": 2,
      "channel": "https://conda.anaconda.org/conda-forge/linux-64",
      "name": "graphicsmagick",
      "subdir": "linux-64",
      "version": "1.3.36"
     },
     "solve": "success",
     "test": "success"
    }
   ]
  },
  {
   "name": "graphicsmagick",
   "platform": "osx-64",
   "status": [
    {
     "implementation": "mamba",
     "package": {
      "build": "hc3d8c12_2",
      "build_number": 2,
      "channel": "https://conda.anaconda.org/conda-forge/osx-64",
      "name": "graphicsmagick",
      "subdir": "osx-64",
      "version": "1.3.36"
     },
     "solve": "success",
     "test": "success"
    }
   ]
  }
 ]
}