{
 "started_at": "2021-11-10T02:31:20+00:00",
 "state": "completed",
 "status": [
  {
   "name": "desman",
   "platform": "linux-64",
   "status": [
    {
     "implementation": "mamba",
     "package": {
      "build": "py38he3b0f8b_4",
      "build_number": 4,
      "channel": "https://conda.anaconda.org/bioconda/linux-64",
      "name": "desman",
      "subdir": "linux-64",
      "version": "2.1"
     },
     "solve": "success",
     "test": "success"
    }
   ]
  },
  {
   "name": "desman",
   "platform": "osx-64",
   "status": [
    {
     "implementation": "mamba",
     "package": {
      "build": "py38h0c2bb6a_4",
      "build_number": 4,
      "channel": "https://conda.anaconda.org/bioconda/osx-64",
      "name": "desman",
      "subdir": "osx-64",
      "version": "2.1"
     },
     "solve": "success",
     "test": "success"
    }
   ]
  }
 ]
}