{
 "started_at": "2021-11-13T14:16:11+00:00",
 "state": "completed",
 "status": [
  {
   "name": "bioconductor-hgu133afrmavecs",
   "platform": "linux-64",
   "status": [
    {
     "implementation": "mamba",
     "package": {
      "build": "r41hdfd78af_9",
      "build_number": 9,
      "channel": "https://conda.anaconda.org/bioconda/noarch",
      "name": "bioconductor-hgu133afrmavecs",
      "subdir": "noarch",
      "version": "1.5.0"
     },
     "solve": "success",
     "test": "success"
    }
   ]
  },
  {
   "name": "bioconductor-hgu133afrmavecs",
   "platform": "osx-64",
   "status": [
    {
     "implementation": "mamba",
     "package": {
      "build": "r41hdfd78af_9",
      "build_number": 9,
      "channel": "https://conda.anaconda.org/bioconda/noarch",
      "name": "bioconductor-hgu133afrmavecs",
      "subdir": "noarch",
      "version": "1.5.0"
     },
     "solve": "success",
     "test": "success"
    }
   ]
  }
 ]
}