{
 "started_at": "2021-11-15T22:16:18+00:00",
 "state": "completed",
 "status": [
  {
   "name": "jolytree",
   "platform": "linux-64",
   "status": [
    {
     "implementation": "mamba",
     "package": {
      "build": "hdfd78af_1",
      "build_number": 1,
      "channel": "https://conda.anaconda.org/bioconda/noarch",
      "name": "jolytree",
      "subdir": "noarch",
      "version": "1.1b"
     },
     "solve": "success",
     "test": "success"
    }
   ]
  },
  {
   "name": "jolytree",
   "platform": "osx-64",
   "status": [
    {
     "implementation": "mamba",
     "package": {
      "build": "hdfd78af_1",
      "build_number": 1,
      "channel": "https://conda.anaconda.org/bioconda/noarch",
      "name": "jolytree",
      "subdir": "noarch",
      "version": "1.1b"
     },
     "solve": "success",
     "test": "success"
    }
   ]
  }
 ]
}